ncirequest/__init__.py
ncirequest/core.py
ncirequest/utils.py
ncirequest-0.1.dist-info/METADATA
ncirequest-0.1.dist-info/WHEEL
ncirequest-0.1.dist-info/top_level.txt
ncirequest-0.1.dist-info/RECORD
