Metadata-Version: 2.1
Name: ncirequest
Version: 0.1
Summary: A package for handling web scraping with retries, user-agent rotation, and proxy support
Author: Your Name
Author-email: your.email@example.com
Classifier: Programming Language :: Python :: 3
Classifier: License :: OSI Approved :: MIT License
Classifier: Operating System :: OS Independent
Requires-Dist: requests
Requires-Dist: cloudscraper
Requires-Dist: selenium
Requires-Dist: webdriver-manager
Requires-Dist: seleniumbase
Requires-Dist: beautifulsoup4
Requires-Dist: tenacity
Requires-Dist: playwright
Requires-Dist: fake-useragent
